<?xml version="1.0" encoding="utf-8"?>
<abapGit version="v1.0.0" serializer="LCL_OBJECT_VIEW" serializer_version="v1.0.0">
 <asx:abap xmlns:asx="http://www.sap.com/abapxml" version="1.0">
  <asx:values>
   <DD25V>
    <VIEWNAME>ZVI_T7IND3</VIEWNAME>
    <AS4LOCAL>A</AS4LOCAL>
    <DDLANGUAGE>E</DDLANGUAGE>
    <AGGTYPE>V</AGGTYPE>
    <ROOTTAB>T7IND3</ROOTTAB>
    <DDTEXT>Dearness allowance consumer price index value</DDTEXT>
    <VIEWCLASS>C</VIEWCLASS>
    <CUSTOMAUTH>C</CUSTOMAUTH>
    <GLOBALFLAG>X</GLOBALFLAG>
   </DD25V>
   <DD26V_TABLE>
    <DD26V>
     <VIEWNAME>ZVI_T7IND3</VIEWNAME>
     <TABNAME>T7IND3</TABNAME>
     <TABPOS>0001</TABPOS>
     <FORTABNAME>T7IND3</FORTABNAME>
    </DD26V>
    <DD26V>
     <VIEWNAME>ZVI_T7IND3</VIEWNAME>
     <TABNAME>T7IND1</TABNAME>
     <TABPOS>0002</TABPOS>
     <FORTABNAME>T7IND3</FORTABNAME>
     <FORFIELD>INDCD</FORFIELD>
     <FORDIR>E</FORDIR>
    </DD26V>
    <DD26V>
     <VIEWNAME>ZVI_T7IND3</VIEWNAME>
     <TABNAME>T7IND9</TABNAME>
     <TABPOS>0003</TABPOS>
     <FORTABNAME>T7IND3</FORTABNAME>
     <FORFIELD>REFCD</FORFIELD>
     <FORDIR>E</FORDIR>
    </DD26V>
   </DD26V_TABLE>
   <DD27P_TABLE>
    <DD27P>
     <VIEWFIELD>MANDT</VIEWFIELD>
     <TABNAME>T7IND3</TABNAME>
     <FIELDNAME>MANDT</FIELDNAME>
     <KEYFLAG>X</KEYFLAG>
     <CHECKTABLE>T000</CHECKTABLE>
     <SHLPORIGIN>P</SHLPORIGIN>
    </DD27P>
    <DD27P>
     <VIEWFIELD>INDCD</VIEWFIELD>
     <TABNAME>T7IND3</TABNAME>
     <FIELDNAME>INDCD</FIELDNAME>
     <KEYFLAG>X</KEYFLAG>
     <CHECKTABLE>T7IND1</CHECKTABLE>
     <SHLPORIGIN>P</SHLPORIGIN>
    </DD27P>
    <DD27P>
     <VIEWFIELD>ENDDA</VIEWFIELD>
     <TABNAME>T7IND3</TABNAME>
     <FIELDNAME>ENDDA</FIELDNAME>
     <KEYFLAG>X</KEYFLAG>
     <SHLPORIGIN>T</SHLPORIGIN>
    </DD27P>
    <DD27P>
     <VIEWFIELD>RFVAL</VIEWFIELD>
     <TABNAME>T7IND3</TABNAME>
     <FIELDNAME>RFVAL</FIELDNAME>
    </DD27P>
    <DD27P>
     <VIEWFIELD>CRVAL</VIEWFIELD>
     <TABNAME>T7IND3</TABNAME>
     <FIELDNAME>CRVAL</FIELDNAME>
    </DD27P>
    <DD27P>
     <VIEWFIELD>REFCD</VIEWFIELD>
     <TABNAME>T7IND3</TABNAME>
     <FIELDNAME>REFCD</FIELDNAME>
     <CHECKTABLE>T7IND9</CHECKTABLE>
     <SHLPORIGIN>P</SHLPORIGIN>
    </DD27P>
    <DD27P>
     <VIEWFIELD>BEGDA</VIEWFIELD>
     <TABNAME>T7IND3</TABNAME>
     <FIELDNAME>BEGDA</FIELDNAME>
     <SHLPORIGIN>T</SHLPORIGIN>
    </DD27P>
   </DD27P_TABLE>
   <DD28J_TABLE>
    <DD28J>
     <VIEWNAME>ZVI_T7IND3</VIEWNAME>
     <LTAB>T7IND1</LTAB>
     <LFIELD>MANDT</LFIELD>
     <OPERATOR>EQ</OPERATOR>
     <RTAB>T7IND3</RTAB>
     <RFIELD>MANDT</RFIELD>
     <SOURCE>F</SOURCE>
     <FRKTAB>T7IND3</FRKTAB>
     <FRKFIELD>INDCD</FRKFIELD>
     <FRKDIR>E</FRKDIR>
    </DD28J>
    <DD28J>
     <VIEWNAME>ZVI_T7IND3</VIEWNAME>
     <LTAB>T7IND1</LTAB>
     <LFIELD>INDCD</LFIELD>
     <OPERATOR>EQ</OPERATOR>
     <RTAB>T7IND3</RTAB>
     <RFIELD>INDCD</RFIELD>
     <SOURCE>F</SOURCE>
     <FRKTAB>T7IND3</FRKTAB>
     <FRKFIELD>INDCD</FRKFIELD>
     <FRKDIR>E</FRKDIR>
    </DD28J>
    <DD28J>
     <VIEWNAME>ZVI_T7IND3</VIEWNAME>
     <LTAB>T7IND9</LTAB>
     <LFIELD>MANDT</LFIELD>
     <OPERATOR>EQ</OPERATOR>
     <RTAB>T7IND3</RTAB>
     <RFIELD>MANDT</RFIELD>
     <SOURCE>F</SOURCE>
     <FRKTAB>T7IND3</FRKTAB>
     <FRKFIELD>REFCD</FRKFIELD>
     <FRKDIR>E</FRKDIR>
    </DD28J>
    <DD28J>
     <VIEWNAME>ZVI_T7IND3</VIEWNAME>
     <LTAB>T7IND9</LTAB>
     <LFIELD>REFCD</LFIELD>
     <OPERATOR>EQ</OPERATOR>
     <RTAB>T7IND3</RTAB>
     <RFIELD>REFCD</RFIELD>
     <SOURCE>F</SOURCE>
     <FRKTAB>T7IND3</FRKTAB>
     <FRKFIELD>REFCD</FRKFIELD>
     <FRKDIR>E</FRKDIR>
    </DD28J>
   </DD28J_TABLE>
  </asx:values>
 </asx:abap>
</abapGit>
